django_systemgroups-1.1.3.dist-info/DESCRIPTION.rst
django_systemgroups-1.1.3.dist-info/METADATA
django_systemgroups-1.1.3.dist-info/RECORD
django_systemgroups-1.1.3.dist-info/WHEEL
django_systemgroups-1.1.3.dist-info/metadata.json
django_systemgroups-1.1.3.dist-info/top_level.txt
systemgroups/__init__.py
systemgroups/admin.py
systemgroups/apps.py
systemgroups/backends.py
systemgroups/base.py
systemgroups/models.py
systemgroups/settings.py
systemgroups/systemgroups.py
systemgroups/tests.py
systemgroups/views.py
systemgroups/migrations/0001_initial.py
systemgroups/migrations/__init__.py
