Metadata-Version: 2.0
Name: django-systemgroups
Version: 1.1.3
Summary: 基于Django实现的系统组。
Home-page: https://github.com/Kidwind/django-systemgroups
Author: Kidwind
Author-email: Kidwind@gmail.com
License: BSD
Keywords: django system groups
Platform: UNKNOWN
Classifier: Development Status :: 3 - Alpha
Classifier: Environment :: Web Environment
Classifier: Framework :: Django
Classifier: Intended Audience :: Developers
Classifier: License :: OSI Approved :: BSD License
Classifier: Operating System :: OS Independent
Classifier: Programming Language :: Python
Classifier: Topic :: Security
Classifier: Programming Language :: Python :: 2.7
Classifier: Programming Language :: Python :: 3.3
Classifier: Programming Language :: Python :: 3.4
Classifier: Programming Language :: Python :: 3.5
